<annotation>
	<folder>frames</folder>
	<filename>image636.jpg</filename>
	<path>/Users/claudiabacaperez/Desktop/mcv-m6-2019-team2/datasets/train/S03/c010/frames/image636.jpg</path>
	<source>
		<database>Unknown</database>
	</source>
	<size>
		<width>1920</width>
		<height>1080</height>
		<depth>3</depth>
	</size>
	<segmented>0</segmented>
	<object>
		<name>car</name>
		<pose>Unspecified</pose>
		<truncated>0</truncated>
		<difficult>0</difficult>
		<bndbox>
			<xmin>264</xmin>
			<ymin>812</ymin>
			<xmax>671</xmax>
			<ymax>1067</ymax>
		</bndbox>
	</object>
	<object>
		<name>car</name>
		<pose>Unspecified</pose>
		<truncated>0</truncated>
		<difficult>0</difficult>
		<bndbox>
			<xmin>811</xmin>
			<ymin>45</ymin>
			<xmax>914</xmax>
			<ymax>91</ymax>
		</bndbox>
	</object>
</annotation>
